LICENSE
MANIFEST.in
README.rst
pushover_cli.py
requirements.in
requirements.txt
setup.py
pushover_cli.egg-info/PKG-INFO
pushover_cli.egg-info/SOURCES.txt
pushover_cli.egg-info/dependency_links.txt
pushover_cli.egg-info/entry_points.txt
pushover_cli.egg-info/requires.txt
pushover_cli.egg-info/top_level.txt