Metadata-Version: 1.1
Name: pushover-cli
Version: 1.0.1
Summary: A simple command-line interface to send Pushover notifications
Home-page: https://github.com/zoni/pushover-cli
Author: Nick Groenen
Author-email: nick@groenen.me
License: MIT
Keywords: pushover api message push service phone android iphone
Platform: UNKNOWN
Classifier: Development Status :: 5 - Production/Stable
Classifier: Environment :: Console
Classifier: Topic :: Utilities
Classifier: Topic :: Communications
Classifier: Topic :: Internet
Classifier: License :: OSI Approved :: MIT License
Classifier: Operating System :: POSIX
Classifier: Programming Language :: Python :: 2.7
Classifier: Programming Language :: Python :: 3
